merkle_zeppelin/__init__.py
merkle_zeppelin/binary.py
merkle_zeppelin/exceptions.py
merkle_zeppelin/merkle.py
merkle_zeppelin/data_io/__init__.py
merkle_zeppelin/data_io/base_exporter.py
merkle_zeppelin/data_io/base_importer.py
merkle_zeppelin/data_io/dto.py
merkle_zeppelin/data_io/json_exporter.py
merkle_zeppelin/data_io/json_importer.py
merkle_zeppelin-1.0.0.dist-info/METADATA
merkle_zeppelin-1.0.0.dist-info/WHEEL
merkle_zeppelin-1.0.0.dist-info/licenses/LICENSE
merkle_zeppelin-1.0.0.dist-info/RECORD
