Metadata-Version: 2.4
Name: merkle-zeppelin
Version: 1.0.0
Summary: MerkleTree implementation
Project-URL: Homepage, https://github.com/akcelero/merkle-zeppelin
Project-URL: Repository, https://github.com/akcelero/merkle-zeppelin
Project-URL: Issues, https://github.com/akcelero/merkle-zeppelin/issues
Author-email: akcelero <akcelero@gmail.com>
License-Expression: MIT
License-File: LICENSE
Keywords: merkle,merkletree,openzeppelin,tree
Classifier: Development Status :: 5 - Production/Stable
Classifier: Intended Audience :: Developers
Classifier: License :: OSI Approved :: MIT License
Classifier: Programming Language :: Python :: 3
Classifier: Programming Language :: Python :: 3 :: Only
Classifier: Programming Language :: Python :: 3.9
Classifier: Programming Language :: Python :: 3.10
Classifier: Programming Language :: Python :: 3.11
Classifier: Programming Language :: Python :: 3.12
Classifier: Topic :: Utilities
Requires-Python: >=3.9
Requires-Dist: eth-abi>=4.0.0
Requires-Dist: pycryptodome>=3.0.0
Requires-Dist: pydantic>=2.11.4
